hanja/__init__.py
hanja/hangul.py
hanja/impl.py
hanja/table.py
hanja/table.yml
hanja-0.15.1.dist-info/METADATA
hanja-0.15.1.dist-info/WHEEL
hanja-0.15.1.dist-info/top_level.txt
hanja-0.15.1.dist-info/RECORD
