Metadata-Version: 2.1
Name: hanja
Version: 0.15.1
Summary: Hangul & Hanja library
Home-page: https://github.com/suminb/hanja
Author: Sumin Byeon
Author-email: suminb@gmail.com
Requires-Dist: pyyaml==6.0.1
Requires-Dist: pytest
Requires-Dist: pytest-cov
Requires-Dist: coveralls
